states/machine.py
states/tools.py
states/__init__.py
states-0.1.13.dist-info/DESCRIPTION.rst
states-0.1.13.dist-info/METADATA
states-0.1.13.dist-info/metadata.json
states-0.1.13.dist-info/RECORD
states-0.1.13.dist-info/top_level.txt
states-0.1.13.dist-info/WHEEL
