Metadata-Version: 2.0
Name: states
Version: 0.1.13
Summary: state machine for python classes
Home-page: UNKNOWN
Author: Lars van Gemerden
Author-email: gemerden@gmail.com
License: MIT License
Keywords: access data structure getter setter deleter iterator utility tool
Platform: UNKNOWN
Classifier: Development Status :: 4 - Beta
Classifier: Intended Audience :: Developers
Classifier: Topic :: Software Development
Classifier: License :: OSI Approved :: MIT License
Classifier: Programming Language :: Python :: 2.7
Classifier: Programming Language :: Python :: 3
Requires-Python: >=2.7, >3
